app/__init__.py
app/adapters/__init__.py
app/adapters/state_adapter.py
app/core/__init__.py
app/core/config.py
app/core/database.py
app/models/__init__.py
app/models/capture.py
app/models/config_schemas.py
app/models/snapshot.py
app/routes/capture.py
app/routes/embeddings.py
app/routes/execution/__init__.py
app/routes/execution/execution_router.py
app/routes/execution/health_router.py
app/routes/execution/history_router.py
app/routes/execution/models.py
app/routes/execution/state_router.py
app/routes/execution/websocket_router.py
app/routes/integration_testing.py
app/routes/pathfinding.py
app/routes/rag.py
app/routes/RAG_API_README.md
app/routes/snapshot_search.py
app/routes/snapshots.py
app/routes/vision_extraction.py
app/services/capture_service.py
app/services/filter_builder.py
app/services/inference/__init__.py
app/services/inference/inference_engine.py
app/services/inference/model_export.py
app/services/rag/__init__.py
app/services/rag/description_service.py
app/services/rag/element_service.py
app/services/rag/export_service.py
app/services/rag/find_rag.py
app/services/rag/generate_embeddings.py
app/services/rag/project_service.py
app/services/rag/search_rag.py
app/services/rag/state_service.py
app/services/rag/transition_service.py
app/services/snapshot_analysis.py
app/services/snapshot_deduplication.py
app/services/snapshot_query.py
app/services/snapshot_recommendations.py
app/services/snapshot_sync.py
app/services/state_coverage.py
app/services/storage/__init__.py
app/services/storage/base.py
app/services/storage/factory.py
app/services/storage/frame_extractor.py
app/services/storage/local.py
app/services/storage/s3.py
qontinui_api-0.2.0.dist-info/METADATA
qontinui_api-0.2.0.dist-info/WHEEL
qontinui_api-0.2.0.dist-info/RECORD
