Metadata-Version: 2.4
Name: qontinui-api
Version: 0.2.0
Summary: REST API service for Qontinui GUI automation (maintenance mode)
License: MIT
Keywords: gui,automation,api,fastapi,qontinui
Author: Joshua Spinak
Author-email: jspinak@alum.mit.edu
Requires-Python: >=3.12,<3.14
Classifier: Development Status :: 7 - Inactive
Classifier: Framework :: FastAPI
Classifier: Intended Audience :: Developers
Classifier: License :: OSI Approved :: MIT License
Classifier: Programming Language :: Python :: 3
Classifier: Programming Language :: Python :: 3.12
Classifier: Programming Language :: Python :: 3.13
Classifier: Topic :: Software Development :: Testing
Requires-Dist: aioboto3 (>=15.5.0,<16.0.0)
Requires-Dist: aiofiles (>=25.1.0,<26.0.0)
Requires-Dist: cors (>=1.0.1,<2.0.0)
Requires-Dist: easyocr (>=1.7.0,<2.0.0)
Requires-Dist: email-validator (>=2.3.0,<3.0.0)
Requires-Dist: fastapi (>=0.124,<0.125)
Requires-Dist: numpy (>=1.26,<2.0)
Requires-Dist: opencv-python (>=4.9,<5.0)
Requires-Dist: passlib[bcrypt] (>=1.7.4,<2.0.0)
Requires-Dist: pillow (>=11,<12)
Requires-Dist: psycopg2-binary (>=2.9.9,<3.0.0)
Requires-Dist: pydantic (>=2.12,<3.0)
Requires-Dist: pydantic-settings (>=2.12,<3.0)
Requires-Dist: python-dotenv (>=1.0.0,<2.0.0)
Requires-Dist: python-jose[cryptography] (>=3.3.0,<4.0.0)
Requires-Dist: python-multipart (>=0.0.9)
Requires-Dist: qdrant-client (>=1.11.0,<2.0.0)
Requires-Dist: redis (>=7.1.0,<8.0.0)
Requires-Dist: slowapi (>=0.1.9,<0.2.0)
Requires-Dist: sqlalchemy (>=2.0.43,<3.0.0)
Requires-Dist: torch (>=2.5,<3.0)
Requires-Dist: torchvision (>=0.20,<0.21)
Requires-Dist: uvicorn[standard] (>=0.38,<0.39)
Project-URL: Documentation, https://github.com/qontinui/qontinui-api#readme
Project-URL: Homepage, https://github.com/qontinui/qontinui-api
Project-URL: Repository, https://github.com/qontinui/qontinui-api
